weatho/__init__.py
weatho/locations.py
weatho/plotting.py
weatho/weather.py
weatho-1.0.1.dist-info/LICENSE
weatho-1.0.1.dist-info/METADATA
weatho-1.0.1.dist-info/WHEEL
weatho-1.0.1.dist-info/top_level.txt
weatho-1.0.1.dist-info/RECORD
