Metadata-Version: 2.1
Name: weatho
Version: 1.0.1
Summary: Download, manage and plot weather data from Darksky / OpenWeatherMap APIs
Home-page: https://github.com/ovinc/weatho
Author: Olivier Vincent
Author-email: ovinc.py@gmail.com
License: BSD 3-Clause License
Keywords: weather,darksky
Platform: UNKNOWN
Classifier: Programming Language :: Python :: 3
Classifier: License :: OSI Approved :: BSD License
Classifier: Operating System :: OS Independent
Requires-Python: >=3.6
Requires-Dist: numpy
Requires-Dist: matplotlib
Requires-Dist: requests
Requires-Dist: importlib-metadata
